{
  "id": "567951390",
  "title": "谬误：反叛权威是青少年发展的自然阶段",
  "type": "article",
  "article_type": "normal",
  "excerpt_title": "",
  "url": "https://api.zhihu.com/articles/567951390",
  "image_url": "https://picx.zhimg.com/v2-5d10f440bafadc3e0cd9a4d0f7a3d6b2_720w.jpg?source=172ae18b",
  "title_image": "https://picx.zhimg.com/v2-5d10f440bafadc3e0cd9a4d0f7a3d6b2_720w.jpg?source=172ae18b",
  "excerpt": "谬误：在青春期，青少年的情绪不稳定，对整个世界产生反感。 事实：「叛逆期」可能是 <a href=\"https://link.zhihu.com/?target=https%3A//supermemo.guru/wiki/Compulsory_schooling\" class=\" wrap external\" target=\"_blank\" rel=\"nofollow noreferrer\">强制学校教育</a>[1]雕刻出来的副产品。影响个人对世界态度最重要的过程是 <a href=\"https://link.zhihu.com/?target=https%3A//supermemo.guru/wiki/Conceptualization\" class=\" wrap external\" target=\"_blank\" rel=\"nofollow noreferrer\">概念化</a>[2]过程，它决定了大脑的结构，以及<a href=\"https://link.zhihu.com/?target=https%3A//supermemo.guru/wiki/Concept_network\" class=\" wrap external\" target=\"_blank\" rel=\"nofollow noreferrer\">概念网络</a>[3]的拓扑结构。这个持续终生的过程似乎没有显示…",
  "created": 1664082047,
  "updated": 1688831410,
  "author": {
    "is_followed": true,
    "avatar_url_template": "https://picx.zhimg.com/v2-d571786b77078321f5f6ef92f4967877.jpg?source=172ae18b",
    "uid": "592323397158703104",
    "user_type": "people",
    "is_following": true,
    "url_token": "L.M.Sherlock",
    "id": "4c592f496dc33822b560b382907ff1d0",
    "description": "欢迎关注 Thoughts Memo 汉化组！我们关注的话题包括但不限于认知科学、知识工作、学习方法、学校教育、理性思考、儿童权利，目前已经完成翻译 1400 多篇文章。\n\n加入汉化组：https://paratranz.cn/projects/3131",
    "name": "Thoughts Memo",
    "is_advertiser": false,
    "headline": "学校≠教育≠技能；文凭溢价=80%信号传递+20%人力资本",
    "gender": -1,
    "url": "https://api.zhihu.com/people/4c592f496dc33822b560b382907ff1d0",
    "avatar_url": "https://pic1.zhimg.com/v2-d571786b77078321f5f6ef92f4967877_l.jpg?source=172ae18b",
    "is_org": false,
    "type": "people",
    "badge": [
      {
        "type": "identity",
        "topics": [],
        "description": "信息技术行业 算法工程师"
      }
    ],
    "badge_v2": {
      "title": "知势榜教育校园领域影响力榜答主",
      "merged_badges": [
        {
          "type": "best",
          "detail_type": "best",
          "title": "社区成就",
          "description": "知势榜教育校园领域影响力榜答主",
          "url": "",
          "sources": [],
          "icon": "",
          "night_icon": "",
          "badge_status": "passed"
        },
        {
          "type": "identity",
          "detail_type": "identity_people",
          "title": "认证",
          "description": "信息技术行业 算法工程师",
          "url": "https://zhuanlan.zhihu.com/p/96956163",
          "sources": [],
          "icon": "",
          "night_icon": "",
          "badge_status": "passed"
        }
      ],
      "detail_badges": [
        {
          "type": "reward",
          "detail_type": "super_activity",
          "title": "社区成就",
          "description": "知势榜教育校园领域影响力榜答主",
          "url": "",
          "sources": [
            {
              "id": "27",
              "token": "",
              "type": "content_potential_category",
              "url": "",
              "name": "知势榜8月",
              "avatar_path": "",
              "avatar_url": "",
              "description": "",
              "priority": 27
            }
          ],
          "icon": "https://picx.zhimg.com/v2-4a07bc69c4bb04444721f35b32125c75_l.png?source=32738c0c",
          "night_icon": "https://picx.zhimg.com/v2-4a07bc69c4bb04444721f35b32125c75_l.png?source=32738c0c",
          "badge_status": "passed"
        },
        {
          "type": "identity",
          "detail_type": "identity_people",
          "title": "已认证的个人",
          "description": "信息技术行业 算法工程师",
          "url": "https://zhuanlan.zhihu.com/p/96956163",
          "sources": [],
          "icon": "https://picx.zhimg.com/v2-2ddc5cc683982648f6f123616fb4ec09_l.png?source=32738c0c",
          "night_icon": "https://pic1.zhimg.com/v2-2ddc5cc683982648f6f123616fb4ec09_l.png?source=32738c0c",
          "badge_status": "passed"
        }
      ],
      "icon": "https://picx.zhimg.com/v2-27bfcba90e66db79ce8768ab807e017e_l.png?source=32738c0c",
      "night_icon": "https://picx.zhimg.com/v2-27bfcba90e66db79ce8768ab807e017e_l.png?source=32738c0c"
    },
    "exposed_medal": {
      "medal_id": "1923758082363757092",
      "medal_name": "知识分享官",
      "avatar_url": "https://pic1.zhimg.com/v2-76ac522e2e055b4f4aa317fbecdcef61_r.png?source=172ae18b",
      "mini_avatar_url": "https://picx.zhimg.com/v2-76ac522e2e055b4f4aa317fbecdcef61_l.png?source=172ae18b",
      "description": "「知乎直答知识库」活动激励徽章",
      "medal_avatar_frame": ""
    }
  },
  "comment_permission": "all",
  "copyright_permission": "need_review",
  "state": "published",
  "ip_info": "广东",
  "image_width": 6000,
  "image_height": 4000,
  "content": "<h2>谬误：</h2><p data-pid=\"-FdzJrRK\">在青春期，青少年的情绪不稳定，对整个世界产生反感。</p><h2>事实：</h2><p data-pid=\"H60zn_Cn\">「叛逆期」可能是<a href=\"https://link.zhihu.com/?target=https%3A//supermemo.guru/wiki/Compulsory_schooling\" class=\" wrap external\" target=\"_blank\" rel=\"nofollow noreferrer\">强制学校教育</a><sup data-text=\"强制学校教育\" data-url=\"https://zhuanlan.zhihu.com/p/351869026\" data-draft-node=\"inline\" data-draft-type=\"reference\" data-numero=\"1\">[1]</sup>雕刻出来的副产品。</p><p data-pid=\"6zblX0wS\">影响个人对世界态度最重要的过程是<a href=\"https://link.zhihu.com/?target=https%3A//supermemo.guru/wiki/Conceptualization\" class=\" wrap external\" target=\"_blank\" rel=\"nofollow noreferrer\">概念化</a><sup data-text=\"泛化与概念化\" data-url=\"https://zhuanlan.zhihu.com/p/264989664\" data-draft-node=\"inline\" data-draft-type=\"reference\" data-numero=\"2\">[2]</sup>过程，它决定了大脑的结构，以及<a href=\"https://link.zhihu.com/?target=https%3A//supermemo.guru/wiki/Concept_network\" class=\" wrap external\" target=\"_blank\" rel=\"nofollow noreferrer\">概念网络</a><sup data-text=\"概念网络\" data-url=\"https://zhuanlan.zhihu.com/p/266541480\" data-draft-node=\"inline\" data-draft-type=\"reference\" data-numero=\"3\">[3]</sup>的拓扑结构。这个持续终生的过程似乎没有显示出会有一个「倾向于反叛的特定阶段」。在青春期的时候，可能会发生一些荷尔蒙、神经和情感的动荡。但这不是一个反叛的阶段。在最坏的情况下，青春期暂时加速的概念化会有破坏性影响，引起一定程度的无序混乱。</p><p data-pid=\"CaI7E8xb\">然而，所谓的「反叛阶段」是由一些外部因素产生的幻觉。主要的力量是<a href=\"https://link.zhihu.com/?target=https%3A//supermemo.guru/wiki/Compulsory_schooling\" class=\" wrap external\" target=\"_blank\" rel=\"nofollow noreferrer\">强制学校教育</a><sup data-text=\"强制学校教育\" data-url=\"https://zhuanlan.zhihu.com/p/351869026\" data-draft-node=\"inline\" data-draft-type=\"reference\" data-numero=\"1\">[1]</sup>。一方面，也确实存在一种反叛的力量，会导致学习负担和来自成人世界要求的增加。青春期的到来可能与进入中学的时间相吻合（如<a href=\"https://link.zhihu.com/?target=https%3A//supermemo.guru/wiki/Closed_systems_of_socialization\" class=\" wrap external\" target=\"_blank\" rel=\"nofollow noreferrer\">封闭系统中的社会化</a><sup data-text=\"封闭系统中的社会化\" data-url=\"https://zhuanlan.zhihu.com/p/584230135\" data-draft-node=\"inline\" data-draft-type=\"reference\" data-numero=\"4\">[4]</sup>中解释的那样）。叛逆的力量被逐渐发展的<a href=\"https://link.zhihu.com/?target=https%3A//supermemo.guru/wiki/Learned_helplessness\" class=\" wrap external\" target=\"_blank\" rel=\"nofollow noreferrer\">习得性无助</a>所抑制。如果「缓缓进入顺从的成人期」的过程足够缓慢，可能就不会产生所谓的反抗阶段。只有无助感。但这种无助感在青春期也可能有戏剧性的后果，如自杀。</p><p data-pid=\"v5eOri6O\">另一个外部力量是即将结束的强制学校教育。当青少年离强制学校教育阶段结束只有 3-4 年时，他们的叛逆情绪会有所缓解。他们觉得自由就在不远处。一些青少年想象大学是教育的最终解放。另一些人想追随比尔·盖茨或史蒂夫·乔布斯或他们的现代版本。有些人只想找一份工作，摆脱成人的管理。</p><p data-pid=\"BiFZ10Sk\">就对学校的反叛而言，15 岁时的外部压力会大到出奇，这时（1）负担极重，（2）自由极远。这个叛逆的高峰期与大脑的发育关系不大。它在很大程度上是一种社会动力学的表现，可以成就或摧毁一个年轻人。矛盾的是，我们以青少年太叛逆为由拒绝给予他们投票权，从而不面对这个谬误。请看：<a href=\"https://link.zhihu.com/?target=https%3A//www.vox.com/future-perfect/2019/9/10/20835327/voting-age-youth-rights-kids-vote\" class=\" wrap external\" target=\"_blank\" rel=\"nofollow noreferrer\">让他们投票！</a><sup data-text=\"儿童应有投票权\" data-url=\"https://zhuanlan.zhihu.com/p/268255239\" data-draft-node=\"inline\" data-draft-type=\"reference\" data-numero=\"5\">[5]</sup></p><p class=\"ztext-empty-paragraph\"><br/></p><blockquote data-pid=\"arr85GBF\"><a href=\"https://link.zhihu.com/?target=http%3A//paratranz.cn/projects/3131\" class=\" wrap external\" target=\"_blank\" rel=\"nofollow noreferrer\">Thoughts Memo</a> 汉化组译制<br/>原文：<a href=\"https://link.zhihu.com/?target=https%3A//supermemo.guru/wiki/Myth%3A_Rebellion_against_authority_is_a_natural_stage_of_teen_development\" class=\" wrap external\" target=\"_blank\" rel=\"nofollow noreferrer\">Myth: Rebellion against authority is a natural stage of teen development - supermemo.guru</a></blockquote>",
  "content_need_truncated": false,
  "force_login_when_click_read_more": false,
  "admin_closed_comment": false,
  "topics": [
    {
      "url": "https://api.zhihu.com/topics/19555471",
      "type": "topic",
      "id": "19555471",
      "name": "青少年"
    },
    {
      "url": "https://api.zhihu.com/topics/19589820",
      "type": "topic",
      "id": "19589820",
      "name": "学校"
    },
    {
      "url": "https://api.zhihu.com/topics/19569335",
      "type": "topic",
      "id": "19569335",
      "name": "学校教育"
    }
  ],
  "voteup_count": 192,
  "voting": 1,
  "heavy_up_status": "allow_heavy_up",
  "column": {
    "description": "该专栏翻译有关记忆，学习，睡眠，创造力，解决问题，脑科学，健康和教育的文章",
    "can_manage": false,
    "intro": "现代学校教育系统批判",
    "is_following": false,
    "url_token": "supermemo-guru-cn",
    "id": "supermemo-guru-cn",
    "articles_count": 356,
    "accept_submission": true,
    "title": "学校教育问题",
    "url": "https://api.zhihu.com/columns/supermemo-guru-cn",
    "comment_permission": "all",
    "created": 1530510592,
    "updated": 1751810952,
    "image_url": "https://picx.zhimg.com/v2-597185044fc216b1f6b0cf3d55439dbb_720w.jpg?source=172ae18b",
    "author": {
      "is_followed": false,
      "avatar_url_template": "https://pic1.zhimg.com/v2-d571786b77078321f5f6ef92f4967877.jpg?source=172ae18b",
      "uid": "592323397158703104",
      "user_type": "people",
      "is_following": false,
      "url_token": "L.M.Sherlock",
      "id": "4c592f496dc33822b560b382907ff1d0",
      "description": "欢迎关注 Thoughts Memo 汉化组！我们关注的话题包括但不限于认知科学、知识工作、学习方法、学校教育、理性思考、儿童权利，目前已经完成翻译 1400 多篇文章。\n\n加入汉化组：https://paratranz.cn/projects/3131",
      "name": "Thoughts Memo",
      "is_advertiser": false,
      "headline": "学校≠教育≠技能；文凭溢价=80%信号传递+20%人力资本",
      "gender": -1,
      "url": "https://api.zhihu.com/people/4c592f496dc33822b560b382907ff1d0",
      "avatar_url": "https://pic1.zhimg.com/v2-d571786b77078321f5f6ef92f4967877_l.jpg?source=172ae18b",
      "is_org": false,
      "type": "people",
      "badge_v2": {
        "title": "",
        "merged_badges": [],
        "detail_badges": [],
        "icon": "",
        "night_icon": ""
      }
    },
    "followers": 1363,
    "type": "column",
    "column_type": "normal"
  },
  "comment_count": 9,
  "contributions": [
    {
      "id": 42635944,
      "state": "accepted",
      "type": "first_publish",
      "column": {
        "description": "该专栏翻译有关记忆，学习，睡眠，创造力，解决问题，脑科学，健康和教育的文章",
        "can_manage": false,
        "intro": "现代学校教育系统批判",
        "is_following": false,
        "url_token": "supermemo-guru-cn",
        "id": "supermemo-guru-cn",
        "articles_count": 356,
        "accept_submission": true,
        "title": "学校教育问题",
        "url": "https://api.zhihu.com/columns/supermemo-guru-cn",
        "comment_permission": "all",
        "created": 1530510592,
        "updated": 1751810952,
        "image_url": "https://picx.zhimg.com/v2-597185044fc216b1f6b0cf3d55439dbb_720w.jpg?source=172ae18b",
        "author": {
          "is_followed": false,
          "avatar_url_template": "https://pic1.zhimg.com/v2-d571786b77078321f5f6ef92f4967877.jpg?source=172ae18b",
          "uid": "592323397158703104",
          "user_type": "people",
          "is_following": false,
          "url_token": "L.M.Sherlock",
          "id": "4c592f496dc33822b560b382907ff1d0",
          "description": "欢迎关注 Thoughts Memo 汉化组！我们关注的话题包括但不限于认知科学、知识工作、学习方法、学校教育、理性思考、儿童权利，目前已经完成翻译 1400 多篇文章。\n\n加入汉化组：https://paratranz.cn/projects/3131",
          "name": "Thoughts Memo",
          "is_advertiser": false,
          "headline": "学校≠教育≠技能；文凭溢价=80%信号传递+20%人力资本",
          "gender": -1,
          "url": "https://api.zhihu.com/people/4c592f496dc33822b560b382907ff1d0",
          "avatar_url": "https://pic1.zhimg.com/v2-d571786b77078321f5f6ef92f4967877_l.jpg?source=172ae18b",
          "is_org": false,
          "type": "people",
          "badge_v2": {
            "title": "",
            "merged_badges": [],
            "detail_badges": [],
            "icon": "",
            "night_icon": ""
          }
        },
        "followers": 1363,
        "type": "column",
        "column_type": "normal"
      }
    }
  ],
  "is_title_image_full_screen": false,
  "upvoted_followees": [],
  "commercial_info": {
    "is_commercial": false,
    "plugin": {}
  },
  "suggest_edit": {
    "status": false,
    "reason": "",
    "tip": "",
    "url": "",
    "title": ""
  },
  "reason": "",
  "annotation_action": [],
  "can_tip": false,
  "tipjarors_count": 0,
  "is_labeled": false,
  "has_publishing_draft": false,
  "is_favorited": false,
  "favlists_count": 175,
  "is_normal": true,
  "status": 0,
  "activity_topping_info": {
    "state": "untopped"
  },
  "share_text": "谬误：反叛权威是青少年发展的自然阶段 - 来自知乎专栏「学校教育问题」，作者: Thoughts Memo https://zhuanlan.zhihu.com/p/567951390 （想看更多？下载 @知乎 App：http://weibo.com/p/100404711598 ）",
  "can_comment": {
    "status": true,
    "reason": ""
  },
  "linkbox": {
    "url": "",
    "category": "",
    "pic": "",
    "title": ""
  },
  "mcn_fp_show": -1,
  "is_visible": true,
  "is_liked": false,
  "liked_count": 58,
  "has_column": true,
  "republishers": [],
  "is_new_link_card": true,
  "emoji_reaction": {
    "like_count": 58,
    "like_has_set": false
  },
  "ab_param": {
    "qa_hidden_voteup": "",
    "rs_interest1": "",
    "zp_zhi_style": ""
  },
  "attached_info": "kgIkCgkyMTQzNDM4NDgSCTU2Nzk1MTM5MBgHIgpJTUFHRV9URVhU",
  "share_guide": {
    "has_positive_bubble": false,
    "has_time_bubble": false,
    "hit_share_guide_cluster": false
  },
  "settings": {
    "table_of_contents": {
      "enabled": true
    }
  },
  "can_reference": false,
  "reaction_instruction": {
    "REACTION_CONTENT_SEGMENT_LIKE": "HIDE"
  },
  "reaction": {
    "statistics": {
      "up_vote_count": 192,
      "down_vote_count": 1,
      "like_count": 58,
      "comment_count": 9,
      "share_count": 0,
      "play_count": 0,
      "interest_play_count": 0,
      "favorites": 175,
      "pv_count": 0,
      "bullet_count": 0,
      "applaud_count": 0,
      "question_follower_count": 0,
      "question_answer_count": 0,
      "plaincontent_vote_up_count": 0,
      "plaincontent_like_count": 0,
      "img_like_count": {
        "v2-5d10f440bafadc3e0cd9a4d0f7a3d6b2": 0
      },
      "subscribe_count": 0,
      "republishers": []
    },
    "relation": {
      "is_author": false,
      "vote": "UP",
      "liked": false,
      "img_liked": {
        "v2-5d10f440bafadc3e0cd9a4d0f7a3d6b2": false
      },
      "faved": false,
      "following": false,
      "subcribed": false,
      "is_navigator_vote": false,
      "current_user_is_navigator": false,
      "vote_next_step": "vote"
    },
    "image_reactions": {
      "v2-5d10f440bafadc3e0cd9a4d0f7a3d6b2": {
        "like_count": 0,
        "is_liked": false
      }
    }
  },
  "interaction_bar_plugins": [
    {
      "type": "comment",
      "comment": {
        "enable": true,
        "placeholder": "发条带图评论"
      }
    }
  ],
  "bar_plugins_flip_time": 3000,
  "podcast_audio_enter": {
    "text": "听内容",
    "text_color": "MapBrand",
    "text_size": 13,
    "action_url": "zhihu://podcast/audio_player/0?contentId=567951390&contentType=article"
  },
  "endorsements": [
    {
      "elements": [
        {
          "type": "IMAGE",
          "image_key": "zhicon_icon_24_column_fill",
          "image_color": {
            "alpha": 1,
            "group": "GBL01A"
          },
          "width": 16,
          "height": 16
        },
        {
          "type": "TEXT",
          "content": "收录于 · 学校教育问题",
          "font_size": 13,
          "font_color": {
            "alpha": 1,
            "group": "GBL01A"
          },
          "is_bold": false,
          "max_line": 1
        },
        {
          "type": "IMAGE",
          "image_key": "zhicon_icon_16_arrow_right",
          "image_color": {
            "alpha": 1,
            "group": "GBL01A"
          },
          "width": 12,
          "height": 12
        }
      ],
      "sub_elements": [],
      "sub_elements_type": "DESCRIPTION",
      "background_color": {
        "alpha": 0.08,
        "group": "GBL01A"
      },
      "action_url": "https://www.zhihu.com/column/supermemo-guru-cn",
      "za": {
        "block_text": "Column",
        "type": "text",
        "text": "收录于 · 学校教育问题"
      }
    }
  ],
  "segment_infos": [
    {
      "pid": "H60zn_Cn",
      "text": "「叛逆期」可能是 强制学校教育[1]雕刻出来的副产品。",
      "marks": [
        {
          "start_index": 0,
          "end_index": 26,
          "seg_info": {
            "seg_ids": [
              "1557397834105573376"
            ],
            "is_like": false,
            "like_count": 3,
            "comment_count": 0,
            "my_comment_count": 0,
            "is_span": false
          }
        }
      ]
    }
  ],
  "allow_segment_interaction": 1,
  "is_navigator": false,
  "navigator_vote": false,
  "vote_next_step": "unvote"
}