{
  "allow_segment_interaction": 1,
  "answer_type": "normal",
  "author": {
    "avatar_url": "https://pic1.zhimg.com/v2-d571786b77078321f5f6ef92f4967877_l.jpg?source=2c26e567",
    "avatar_url_template": "https://picx.zhimg.com/v2-d571786b77078321f5f6ef92f4967877.jpg?source=2c26e567",
    "badge": [
      {
        "description": "信息技术行业 算法工程师",
        "topics": [],
        "type": "identity"
      }
    ],
    "badge_v2": {
      "detail_badges": [
        {
          "badge_status": "passed",
          "description": "知势榜教育校园领域影响力榜答主",
          "detail_type": "super_activity",
          "icon": "https://pic1.zhimg.com/v2-4a07bc69c4bb04444721f35b32125c75_l.png?source=32738c0c",
          "night_icon": "https://pic1.zhimg.com/v2-4a07bc69c4bb04444721f35b32125c75_l.png?source=32738c0c",
          "sources": [
            {
              "avatar_path": "",
              "avatar_url": "",
              "description": "",
              "id": "27",
              "name": "知势榜8月",
              "priority": 27,
              "token": "",
              "type": "content_potential_category",
              "url": ""
            }
          ],
          "title": "社区成就",
          "type": "reward",
          "url": ""
        },
        {
          "badge_status": "passed",
          "description": "信息技术行业 算法工程师",
          "detail_type": "identity_people",
          "icon": "https://pic1.zhimg.com/v2-2ddc5cc683982648f6f123616fb4ec09_l.png?source=32738c0c",
          "night_icon": "https://pic1.zhimg.com/v2-2ddc5cc683982648f6f123616fb4ec09_l.png?source=32738c0c",
          "sources": [],
          "title": "已认证的个人",
          "type": "identity",
          "url": "https://zhuanlan.zhihu.com/p/96956163"
        }
      ],
      "icon": "https://picx.zhimg.com/v2-27bfcba90e66db79ce8768ab807e017e_l.png?source=32738c0c",
      "merged_badges": [
        {
          "badge_status": "passed",
          "description": "知势榜教育校园领域影响力榜答主",
          "detail_type": "best",
          "icon": "",
          "night_icon": "",
          "sources": [],
          "title": "社区成就",
          "type": "best",
          "url": ""
        },
        {
          "badge_status": "passed",
          "description": "信息技术行业 算法工程师",
          "detail_type": "identity_people",
          "icon": "",
          "night_icon": "",
          "sources": [],
          "title": "认证",
          "type": "identity",
          "url": "https://zhuanlan.zhihu.com/p/96956163"
        }
      ],
      "night_icon": "https://pic1.zhimg.com/v2-27bfcba90e66db79ce8768ab807e017e_l.png?source=32738c0c",
      "title": "知势榜教育校园领域影响力榜答主"
    },
    "gender": -1,
    "headline": "维特根斯坦的 fan",
    "id": "4c592f496dc33822b560b382907ff1d0",
    "is_advertiser": false,
    "is_org": false,
    "is_privacy": false,
    "name": "Thoughts Memo",
    "type": "people",
    "url": "https://www.zhihu.com/api/v4/people/4c592f496dc33822b560b382907ff1d0",
    "url_token": "L.M.Sherlock",
    "user_type": "people"
  },
  "biz_ext": {
    "share_guide": {
      "has_positive_bubble": false,
      "has_time_bubble": false,
      "hit_share_guide_cluster": false
    }
  },
  "comment_count": 9,
  "content": "<h2>不是。</h2><p data-pid=\"SAB8DyuV\">社会责任心可以有很多实现的方式，比如举报公司非法加班、给贫困儿童捐款、确保单位招人公平等等。在社交媒体上表现自己对时政、社会热点的关心，实际上对真正需要帮助的人微不足道，还浪费自己时间，损失了做那些真正能够有效帮助他人的事情的机会成本。</p><p data-pid=\"kXR3kWtE\">这并不是我原创的观点，而是 Christopher Freiman 教授在他的书 <i>Why It’s OK to Ignore Politics</i> 中提出的。</p><figure data-size=\"normal\"><noscript><img src=\"https://picx.zhimg.com/50/v2-def4867a6c60c5ce583d06547e55bc2a_720w.jpg?source=2c26e567\" data-caption=\"\" data-size=\"normal\" data-rawwidth=\"1086\" data-rawheight=\"1670\" data-original-token=\"v2-def4867a6c60c5ce583d06547e55bc2a\" data-default-watermark-src=\"https://picx.zhimg.com/50/v2-f06bc7cc6c56ceeb5c05cdbeadcc50ff_720w.jpg?source=2c26e567\" class=\"origin_image zh-lightbox-thumb\" width=\"1086\" data-original=\"https://picx.zhimg.com/v2-def4867a6c60c5ce583d06547e55bc2a_r.jpg?source=2c26e567\"/></noscript><img src=\"data:image/svg+xml;utf8,&lt;svg xmlns=&#39;http://www.w3.org/2000/svg&#39; width=&#39;1086&#39; height=&#39;1670&#39;&gt;&lt;/svg&gt;\" data-caption=\"\" data-size=\"normal\" data-rawwidth=\"1086\" data-rawheight=\"1670\" data-original-token=\"v2-def4867a6c60c5ce583d06547e55bc2a\" data-default-watermark-src=\"https://picx.zhimg.com/50/v2-f06bc7cc6c56ceeb5c05cdbeadcc50ff_720w.jpg?source=2c26e567\" class=\"origin_image zh-lightbox-thumb lazy\" width=\"1086\" data-original=\"https://picx.zhimg.com/v2-def4867a6c60c5ce583d06547e55bc2a_r.jpg?source=2c26e567\" data-actualsrc=\"https://picx.zhimg.com/50/v2-def4867a6c60c5ce583d06547e55bc2a_720w.jpg?source=2c26e567\"/></figure><h2>表现关心时政，对于对抗不公影响有限</h2><p data-pid=\"Dcask2iP\">如果你出于社会责任感，为了努力消除政府所导致的不公，而去关心时政、社会热点，那么，我想提醒你，你表现出来的关心可能对别人毫无影响。大部分人都和我一样，在现实中没有什么影响力。你可以自己想一想，自己通过表达对这些事情的关心，有没有成功说服更多人也来一起关心，最后让不公的事情得到解决？（丰县、承德、郑州，等等等等）在社交平台上表达你的关心，大多数情况下不会引起什么水花，少数情况下还可能引来一群仅仅想要刁难你的人来发表相反观点的评论。我就被扣过毒公知、反动文人、美国间谍等等的帽子。</p><h2>表现关心时政是有机会成本的</h2><p data-pid=\"M7DT4wUH\">你可能听说过，天下没有免费的午餐。这并不是说你不能不花钱就吃到午餐，当然可以。关键在于，你总得为了得到某样东西而放弃另一样东西——比如，那顿午餐会占用你的时间和胃容量。</p><p data-pid=\"JkevJTx3\">同样地，你生活中用于关心政治的那一部分，就是没用于其他帮助人的方式的那一部分。因此，不关心政治的一个关键原因就是其机会成本——花时间观看新闻、发评论和写帖子，就是没用在能带来更多益处的事情上的时间。</p><p data-pid=\"0XVQvQ8o\">对我而言，有时间关心政治，不如做好本职工作，再写几个开源项目，和朋友一起翻译高质量材料，反而能够帮助到更多人。</p><h2>只关心不行动，反而是一种负面的表达</h2><p data-pid=\"Br1EcSqe\">如果总是表达对时政、社会热点的关心，却不去做能有效改善社会公正的事情，反而会传递一种道德上有害的信息：你为了表达你在关心别人，而放弃了帮助别人的机会。举个例子：</p><p data-pid=\"rFCmXkPi\">你在街上遇到一个挨饿的小孩，他向你伸手要钱买吃的。你口袋里确实有点钱，但犹豫不决。为什么呢？因为你正打算用这些钱买一件印有「救济饥民」的文化衫，钱不够两头都照顾。如果你为了买这件文化衫而让小孩继续挨饿，这无异于是在做错事，更别提这样做会让小孩受到本可以轻易避免的伤害。用哲学家 David Schmidtz 的话来说，如果你只是想显示你有好心，那你其实一点儿好心也没有。</p><h2>难道我不能抱怨吗？</h2><p data-pid=\"uFkTBVTj\">可以的。即使你平时不关心时政，你依然可以抱怨它带来的伤害。</p><p data-pid=\"5n105a8h\">当你有机会改变某个结果，但选择不这么做时，你就失去了抱怨这个结果的权利。然而，对于你无法控制的不良或不公平的结果，你有权抱怨。由于你关心政治通常并不能让你对政治结果施加控制，因此你无需关心政治就可以抱怨政治。</p><p data-pid=\"xlPBeTsj\">为了支持这一观点，想象一下你和学校食堂服务员的以下对话：</p><blockquote data-pid=\"JYkgOJrg\">服务员：我们有严格的政策，只供应百事可乐。 <br/>你：哎，我不喜欢百事。 <br/>服务员：嘿，如果你不点别的，你就没资格抱怨。<br/>你：好的，那我能要一瓶可口可乐吗？ <br/>服务员：不行，你没听见我说吗？我们只供应百事。但至少你现在可以抱怨了。</blockquote><p data-pid=\"hq77NaHW\">不用说，这将是一场很奇怪的对话。你是否有理由抱怨这个一成不变的「只供应百事」的政策，与你是否做出徒劳的尝试去点一瓶可口可乐无关。你完全可以仅仅因为这个政策不妥而进行抱怨。</p><p data-pid=\"AzPGNKuU\">然而，有一个更有力的反驳观点：在不关心的同时抱怨，近乎于一种虚伪。一方面，你的不关心表达了这样一种态度，即政治不重要，或者不值得你花时间；另一方面，你的抱怨却表达了相反的态度，即它确实重要，而且值得你花时间。</p><p data-pid=\"2Th9KVR5\">作者对此的回应是：你可以不关心政治，但这并不意味着你认为政治不重要。你之所以不关心政治，可能是因为你怀疑自己的关心是否能有效地对抗不公。比如，有个小行星要砸向地球，而你不去祈愿小行星改变轨迹，因为你怀疑祈愿能否真的改变小行星的轨迹。我们不会因此推断，「不祈愿」的人因此认为小行星不重要，从而失去了抱怨小行星造成的伤害的权利。同样地，我们也不应该假设不关心政治的人因此认为政治不重要，从而失去了抱怨政治造成的伤害的权利。实际上，如果为减轻由糟糕的治理造成或允许的伤害而采取直接行动，那这正是你认为政治重要的表现。因此，即使是不关心政治的人，也应该有权利对政治体制表达自己的不满。</p><h2>结语</h2><p data-pid=\"PVyIoVEE\">这本书花了我长假来回两趟动车的时间才看完，内容有点多，所以这里就不一一列出书中观点了。感兴趣的朋友可以自己去 z-lib 上找一下。</p><p data-pid=\"sDq8uoEe\">要说这本书对我最大的影响，那就是这个了：</p><figure data-size=\"normal\"><noscript><img src=\"https://pic1.zhimg.com/50/v2-f43a525e4c893ae4efc4ab45c20021a6_720w.jpg?source=2c26e567\" data-caption=\"\" data-size=\"normal\" data-rawwidth=\"1762\" data-rawheight=\"1588\" data-original-token=\"v2-f43a525e4c893ae4efc4ab45c20021a6\" data-default-watermark-src=\"https://pic1.zhimg.com/50/v2-525336de98e028362f8ccbe1d6f18842_720w.jpg?source=2c26e567\" class=\"origin_image zh-lightbox-thumb\" width=\"1762\" data-original=\"https://pic1.zhimg.com/v2-f43a525e4c893ae4efc4ab45c20021a6_r.jpg?source=2c26e567\"/></noscript><img src=\"data:image/svg+xml;utf8,&lt;svg xmlns=&#39;http://www.w3.org/2000/svg&#39; width=&#39;1762&#39; height=&#39;1588&#39;&gt;&lt;/svg&gt;\" data-caption=\"\" data-size=\"normal\" data-rawwidth=\"1762\" data-rawheight=\"1588\" data-original-token=\"v2-f43a525e4c893ae4efc4ab45c20021a6\" data-default-watermark-src=\"https://pic1.zhimg.com/50/v2-525336de98e028362f8ccbe1d6f18842_720w.jpg?source=2c26e567\" class=\"origin_image zh-lightbox-thumb lazy\" width=\"1762\" data-original=\"https://pic1.zhimg.com/v2-f43a525e4c893ae4efc4ab45c20021a6_r.jpg?source=2c26e567\" data-actualsrc=\"https://pic1.zhimg.com/50/v2-f43a525e4c893ae4efc4ab45c20021a6_720w.jpg?source=2c26e567\"/></figure><figure data-size=\"normal\"><noscript><img src=\"https://pic1.zhimg.com/50/v2-22c93d9010bef384ceafb85b6d63f0ef_720w.jpg?source=2c26e567\" data-caption=\"\" data-size=\"normal\" data-rawwidth=\"740\" data-rawheight=\"972\" data-original-token=\"v2-22c93d9010bef384ceafb85b6d63f0ef\" data-default-watermark-src=\"https://picx.zhimg.com/50/v2-0262acd37670b73f41bebd36d326f246_720w.jpg?source=2c26e567\" class=\"origin_image zh-lightbox-thumb\" width=\"740\" data-original=\"https://picx.zhimg.com/v2-22c93d9010bef384ceafb85b6d63f0ef_r.jpg?source=2c26e567\"/></noscript><img src=\"data:image/svg+xml;utf8,&lt;svg xmlns=&#39;http://www.w3.org/2000/svg&#39; width=&#39;740&#39; height=&#39;972&#39;&gt;&lt;/svg&gt;\" data-caption=\"\" data-size=\"normal\" data-rawwidth=\"740\" data-rawheight=\"972\" data-original-token=\"v2-22c93d9010bef384ceafb85b6d63f0ef\" data-default-watermark-src=\"https://picx.zhimg.com/50/v2-0262acd37670b73f41bebd36d326f246_720w.jpg?source=2c26e567\" class=\"origin_image zh-lightbox-thumb lazy\" width=\"740\" data-original=\"https://picx.zhimg.com/v2-22c93d9010bef384ceafb85b6d63f0ef_r.jpg?source=2c26e567\" data-actualsrc=\"https://pic1.zhimg.com/50/v2-22c93d9010bef384ceafb85b6d63f0ef_720w.jpg?source=2c26e567\"/></figure><blockquote data-pid=\"793rXJdy\">PS: 我也给 Wikipedia、Khan Academy、Andy Matuschak 捐过款，不过都没这次捐的多。</blockquote><p data-pid=\"D8Z8GZLA\">说来好笑，我有八万多关注者，而在知乎上每个月也就收入两百多块。与其放在知乎钱包里发霉，不如捐给贫困儿童，真正帮助到他们（他们肯定没有条件看我的知乎）。这也算不愧对我自己签名中「改善教育公平」这一句话了。</p><figure data-size=\"normal\"><noscript><img src=\"https://pica.zhimg.com/50/v2-ee2e9823f80b8ed503b36789873a381d_720w.jpg?source=2c26e567\" data-caption=\"\" data-size=\"normal\" data-rawwidth=\"2198\" data-rawheight=\"680\" data-original-token=\"v2-ee2e9823f80b8ed503b36789873a381d\" data-default-watermark-src=\"https://picx.zhimg.com/50/v2-07fa7b11800fa25e5a30a6377743d3e3_720w.jpg?source=2c26e567\" class=\"origin_image zh-lightbox-thumb\" width=\"2198\" data-original=\"https://pic1.zhimg.com/v2-ee2e9823f80b8ed503b36789873a381d_r.jpg?source=2c26e567\"/></noscript><img src=\"data:image/svg+xml;utf8,&lt;svg xmlns=&#39;http://www.w3.org/2000/svg&#39; width=&#39;2198&#39; height=&#39;680&#39;&gt;&lt;/svg&gt;\" data-caption=\"\" data-size=\"normal\" data-rawwidth=\"2198\" data-rawheight=\"680\" data-original-token=\"v2-ee2e9823f80b8ed503b36789873a381d\" data-default-watermark-src=\"https://picx.zhimg.com/50/v2-07fa7b11800fa25e5a30a6377743d3e3_720w.jpg?source=2c26e567\" class=\"origin_image zh-lightbox-thumb lazy\" width=\"2198\" data-original=\"https://pic1.zhimg.com/v2-ee2e9823f80b8ed503b36789873a381d_r.jpg?source=2c26e567\" data-actualsrc=\"https://pica.zhimg.com/50/v2-ee2e9823f80b8ed503b36789873a381d_720w.jpg?source=2c26e567\"/></figure><p data-pid=\"xDVZGprp\">我自己也依然会继续写知乎，翻译一些教育相关的资料，写一些自学教程，帮助每一个需要的人。顺便还可以把知乎收入捐给贫困儿童。</p><p data-pid=\"NykVj1RZ\">而我自己的本职工作——研究记忆算法——也会继续下去，帮助更多使用间隔重复的学习者节约时间。自由学习也好，应付考试也罢，这项学习技术，只有掌握在每个学习者手里，才能发挥最大的作用。</p><p data-pid=\"N3LY0_LC\">之前有读者朋友想要给我打赏，支持我的工作，我觉得大可不必。如果你也想要促进教育公平，那就把这笔钱捐给更有需要的人吧。</p><p data-pid=\"Zky-kF9W\">教育公平，任重道远。</p>",
  "content_need_truncated": false,
  "created_time": 1696727137,
  "excerpt": "不是。社会责任心可以有很多实现的方式，比如举报公司非法加班、给贫困儿童捐款、确保单位招人公平等等。在社交媒体上表现自己对时政、社会热点的关心，实际上对真正需要帮助的人微不足道，还浪费自己时间，损失了做那些真正能够有效帮助他人的事情的机会成本。 这并不是我原创的观点，而是 Christopher Freiman 教授在他的书 Why It’s OK to Ignore Politics 中提出的。 [图片] 表现关心时政，对于对抗不公影响有限如果你出于社会责任…",
  "extras": "",
  "force_login_when_click_read_more": false,
  "id": "3240833580",
  "is_collapsed": false,
  "is_contain_ai_content": false,
  "is_copyable": true,
  "is_jump_native": false,
  "podcast_audio_enter": {
    "action_url": "zhihu://podcast/audio_player/0?contentId=3240833580&contentType=answer&subType=&entrance=detail_page",
    "sub_type": "",
    "text": "听内容",
    "text_color": "MapBrand",
    "text_size": 13
  },
  "question": {
    "created": 1395980827,
    "detail": "有些人不喜欢关注时政热点，感觉这一切都与自己无关，与这个世界有隔阂，是否是因为缺乏社会责任感的缘故？特别指出，我不歧视这类人，只是想问一下，这算不算一种心理问题？",
    "id": "23192887",
    "question_type": "normal",
    "relationship": {},
    "title": "不关心时政、社会热点，是缺乏社会责任心的体现吗？",
    "type": "question",
    "updated_time": 1395980827,
    "url": "https://www.zhihu.com/api/v4/questions/23192887"
  },
  "relationship": {
    "upvoted_followees": []
  },
  "type": "answer",
  "updated_time": 1696727137,
  "url": "https://www.zhihu.com/api/v4/answers/3240833580",
  "voteup_count": 97
}